ZxSci/MathWork.py
ZxSci/Uncertainty.py
ZxSci/__init__.py
ZxSci/getFunction.py
ZxSci/get_file.py
ZxSci/showData.py
ZxSci-0.2.3.dist-info/LICENSE
ZxSci-0.2.3.dist-info/METADATA
ZxSci-0.2.3.dist-info/WHEEL
ZxSci-0.2.3.dist-info/top_level.txt
ZxSci-0.2.3.dist-info/RECORD
