Metadata-Version: 2.1
Name: ZxSci
Version: 0.2.3
Summary: 一个帮助理工科本科学生进行简化计算的库
Home-page: https://github.com/pypa/sampleproject
Author: Larry
Author-email: 1140091006@qq.com
License: MIT Licence
Platform: UNKNOWN
Classifier: Programming Language :: Python :: 3
Classifier: License :: OSI Approved :: MIT License
Classifier: Operating System :: OS Independent
License-File: LICENSE
